{"cameraMode":{"drawMode":0,"name":"Shaded","section":"Shading Mode"},"sceneLighting":true,"audioPlay":false,"sceneViewState":{"m_AlwaysRefresh":false,"showFog":true,"showSkybox":true,"showFlares":true,"showImageEffects":true,"showParticleSystems":true,"showVisualEffectGraphs":true,"m_FxEnabled":true},"in2DMode":false,"pivot":{"x":100.40457153320313,"y":4.635814666748047,"z":42.29528045654297},"rotation":{"x":-0.5310393571853638,"y":-0.000761678908020258,"z":0.0004850292461924255,"w":-0.8473790287971497},"size":38.51188278198242,"orthographic":false}